AUTHORS
CHANGELOG.txt
DESCRIPTION
LICENSE
MANIFEST.in
README.rst
requirements.txt
runtests.py
setup.cfg
setup.py
test_requirements.txt
tox.ini
eckerd-django-google-sso/__init__.py
eckerd-django-google-sso/models.py
eckerd-django-google-sso/urls.py
eckerd-django-google-sso/views.py
eckerd-django-google-sso/management/__init__.py
eckerd-django-google-sso/management/commands/__init__.py
eckerd-django-google-sso/management/commands/hello.py
eckerd-django-google-sso/migrations/0001_initial.py
eckerd-django-google-sso/migrations/__init__.py
eckerd-django-google-sso/static/.empty
eckerd-django-google-sso/static/eckerd-django-google-sso/.empty
eckerd-django-google-sso/templates/eckerd-django-google-sso/.empty
eckerd-django-google-sso/templatetags/__init__.py
eckerd-django-google-sso/templatetags/backend_utils.py
eckerd-django-google-sso/tests/__init__.py
eckerd-django-google-sso/tests/models_tests.py
eckerd-django-google-sso/tests/settings.py
eckerd-django-google-sso/tests/test_settings.py
eckerd-django-google-sso/tests/urls.py
eckerd-django-google-sso/tests/test_app/__init__.py
eckerd-django-google-sso/tests/test_app/models.py
eckerd-django-google-sso/tests/test_app/templates/400.html
eckerd-django-google-sso/tests/test_app/templates/500.html
eckerd_django_google_sso.egg-info/PKG-INFO
eckerd_django_google_sso.egg-info/SOURCES.txt
eckerd_django_google_sso.egg-info/dependency_links.txt
eckerd_django_google_sso.egg-info/requires.txt
eckerd_django_google_sso.egg-info/top_level.txt