Metadata-Version: 1.0
Name: eckerd-django-google-sso
Version: 0.0.1
Summary: A reusable django application for google sso
